[
{
    "nick" : "Chleba_",
    "date": "12.decembra.2023",
    "uiid" : "f297e489-1293-45cc-99ed-30d623bbd30e"
},
{
    "nick" : "Chaboy_",
    "date": "12.decembra.2023",
    "uiid" : "53301208-1b83-4532-9c78-d4bf46096178"
},
{
    "nick" : "DoubleQ23",
    "date": "12.decembra.2023",
    "uiid" : "3b473166-f14c-4b4b-94f9-e1a04e260feb"
},
{
    "nick" : "lucwya",
    "date": "14.decembra.2023",
    "uiid" : "lucwya"
},
{
    "nick" : "MLP12345",
    "date": "12.decembra.2023",
    "uiid" : "MLP12345"
},
{
    "nick" : "MackoodTrixona",
    "date": "14.decembra.2023",
    "uiid" : "MackoodTrixona"
},
{
    "nick" : "Angryman097",
    "date": "13.decembra.2023",
    "uiid" : "9c375620-afbc-46e2-b309-dfa8c6f014f7"
},
{
    "nick" : "BarbarMatko",
    "date": "14.decembra.2023",
    "uiid" : "BarbarMatko"
},
{
    "nick" : "trashmao",
    "date": "13.decembra.2023",
    "uiid" : "0340c0e4-97f5-41c5-8b7a-3d963a1dd096"
},
{
    "nick" : "Kingfilipsvk",
    "date": "14.decembra.2023",
    "uiid" : "6d4d2e90-fc4e-4934-a0ba-103b724d82d8"
},
{
    "nick" : "CuzImTheKing",
    "date": "14.decembra.2023",
    "uiid" : "72418452-0e4d-4dc0-891f-1045fb75dd77"
},
{
    "nick" : "IamTomas_",
    "date": "15.decembra.2023",
    "uiid" : "b292cfbc-25bb-4546-9ef7-b5c4152c08fb"
}

]